{
	"class" : {
		"extent" : "EstebanLorenzano 8/3/2015 18:57",
		"title" : "EstebanLorenzano 4/28/2014 10:18" },
	"instance" : {
		"buildAreaMorph" : "EstebanLorenzano 7/30/2015 17:08",
		"buildBrowser" : "EstebanLorenzano 6/9/2014 17:59",
		"buildInputMorph" : "EstebanLorenzano 7/30/2015 17:07",
		"buildToolBarOn:" : "EstebanLorenzano 5/29/2014 10:04",
		"clearContents" : "EstebanLorenzano 5/30/2014 14:46",
		"closeSession" : "EstebanLorenzano 6/5/2014 11:31",
		"closeSessionAndCleanUpDisplay" : "EstebanLorenzano 8/4/2015 18:38",
		"connectTo:" : "EstebanLorenzano 6/9/2014 19:28",
		"dataReceived:" : "EstebanLorenzano 5/13/2014 17:20",
		"dataSend:" : "EstebanLorenzano 6/5/2014 11:32",
		"disconnect" : "EstebanLorenzano 8/3/2015 17:13",
		"game" : "EstebanLorenzano 5/29/2014 09:39",
		"isConnected" : "EstebanLorenzano 6/5/2014 11:32",
		"isRunning" : "EstebanLorenzano 6/5/2014 13:26",
		"open" : "EstebanLorenzano 8/4/2015 17:43",
		"openAndConnectTo:" : "EstebanLorenzano 6/9/2014 19:30",
		"postOpen" : "EstebanLorenzano 8/4/2015 17:43",
		"prepareDisplayAfterConnect" : "EstebanLorenzano 6/5/2014 11:29",
		"replaceKeyBindingsWith:" : "EstebanLorenzano 8/4/2015 17:38",
		"send:" : "EstebanLorenzano 6/5/2014 13:26",
		"session" : "EstebanLorenzano 6/5/2014 11:31",
		"sessionClosed:" : "EstebanLorenzano 5/29/2014 21:03",
		"transmitFocus" : "EstebanLorenzano 5/16/2014 10:44" } }
