{
	"instance" : {
		"do:while:until:" : "EstebanLorenzano 6/29/2016 08:52",
		"send:" : "EstebanLorenzano 6/29/2016 08:20",
		"do:whileAnyOf:untilAnyOf:" : "EstebanLorenzano 6/29/2016 08:59",
		"dataReceived:" : "EstebanLorenzano 6/29/2016 08:59",
		"do:untilAnyOf:" : "EstebanLorenzano 6/29/2016 08:39",
		"do:whileAnyOf:until:" : "EstebanLorenzano 6/29/2016 08:53",
		"do:until:" : "EstebanLorenzano 6/29/2016 08:38",
		"execute:" : "EstebanLorenzano 6/29/2016 08:50",
		"initializeTerminal:" : "EstebanLorenzano 6/29/2016 08:19",
		"terminal" : "EstebanLorenzano 6/29/2016 08:58",
		"do:while:untilAnyOf:" : "EstebanLorenzano 6/29/2016 08:53",
		"waiting" : "EstebanLorenzano 6/29/2016 08:57"
	},
	"class" : {
		"on:" : "EstebanLorenzano 6/29/2016 08:19"
	}
}